dlengine/__init__.py
dlengine/bridger.py
dlengine/comm.py
dlengine/data_sampler.py
dlengine/defaults.py
dlengine/evaluator.py
dlengine/hooks.py
dlengine/launch.py
dlengine/lr_scheduler.py
dlengine/train_loop.py
dlengine/utils/__init__.py
dlengine/utils/checkpoint.py
dlengine/utils/collect_env.py
dlengine/utils/env.py
dlengine/utils/events.py
dlengine/utils/file_io.py
dlengine/utils/history_buffer.py
dlengine/utils/log.py
dlengine/utils/precision_bn.py
dlengine/utils/testing.py
dlengine/utils/timer.py
dlengine-0.1.0.dist-info/LICENSE
dlengine-0.1.0.dist-info/METADATA
dlengine-0.1.0.dist-info/WHEEL
dlengine-0.1.0.dist-info/top_level.txt
dlengine-0.1.0.dist-info/RECORD
