Metadata-Version: 2.1
Name: dlengine
Version: 0.1.0
Summary: dlengine is a trainning engine targeting to separating miscellaneous trainning things from modeling.
Home-page: https://github.com/pypa/sampleproject
Author: zeyu huang
Author-email: zeyu_huang@163.com
License: UNKNOWN
Platform: UNKNOWN
Classifier: Programming Language :: Python :: 3
Classifier: License :: OSI Approved :: MIT License
Classifier: Operating System :: OS Independent
Requires-Python: >=3.6
License-File: LICENSE
